setup.cfg
setup.py
precis/__init__.py
precis/abbreviate.py
precis/base.py
precis/evaluate.py
precis/generate.py
precis/plot.py
precis/stats.py
precis/version.py
precis.egg-info/PKG-INFO
precis.egg-info/SOURCES.txt
precis.egg-info/dependency_links.txt
precis.egg-info/requires.txt
precis.egg-info/top_level.txt