Metadata-Version: 1.1
Name: precis
Version: 0.1.0
Summary: Genetic algorithm-based measure abbreviation in Python.
Home-page: http://github.com/tyarkoni/precis
Author: Tal Yarkoni
Author-email: tyarkoni@gmail.com
License: UNKNOWN
Download-URL: https://github.com/tyarkoni/precis/archive/0.1.0.tar.gz
Platform: UNKNOWN
